tidy_cli/__init__.py
tidy_cli/helpers.py
tidy_cli/main_cli.py
tidy_cli/commons/__init__.py
tidy_cli/commons/settings.py
tidy_cli/lint_cli/__init__.py
tidy_cli/lint_cli/cli.py
tidy_cli/lint_cli/helpers.py
tidy_cli/pytest_cli/__init__.py
tidy_cli/pytest_cli/cli.py
tidy_cli/pytest_cli/helpers.py
tidy_cli-0.1.6.dist-info/METADATA
tidy_cli-0.1.6.dist-info/WHEEL
tidy_cli-0.1.6.dist-info/entry_points.txt
tidy_cli-0.1.6.dist-info/licenses/LICENSE
tidy_cli-0.1.6.dist-info/RECORD
