Metadata-Version: 2.4
Name: tidy-cli
Version: 0.1.6
Summary: CLI tool for managing linting, formatting and testing
Project-URL: Repository, https://github.com/AlfredoCinelli/tidy-cli
Project-URL: Documentation, https://alfredocinelli.github.io/tidy-cli/
Project-URL: Changelog, https://github.com/AlfredoCinelli/tidy-cli/blob/main/CHANGELOG.md
Author-email: Alfredo Cinelli <alfredocinelli96@gmail.com>
License: MIT
License-File: LICENSE
Classifier: Development Status :: 4 - Beta
Classifier: Intended Audience :: Developers
Classifier: License :: OSI Approved :: MIT License
Classifier: Operating System :: OS Independent
Classifier: Programming Language :: Python :: 3
Classifier: Programming Language :: Python :: 3.10
Classifier: Programming Language :: Python :: 3.11
Classifier: Programming Language :: Python :: 3.12
Classifier: Topic :: Software Development :: Libraries
Requires-Python: >=3.10
Requires-Dist: coverage[toml]>=7.9.2
Requires-Dist: flake8-pyproject>=1.2.3
Requires-Dist: mypy>=1.16.1
Requires-Dist: pydoclint[flake8]>=0.6.6
Requires-Dist: pytest-sugar>=1.0.0
Requires-Dist: pytest>=8.4.1
Requires-Dist: rich>=13.0.0
Requires-Dist: ruff>=0.12.2
Requires-Dist: typer>=0.16.0
